pytest_extra_durations.py
pytest_extra_durations-0.1.3.dist-info/LICENSE
pytest_extra_durations-0.1.3.dist-info/METADATA
pytest_extra_durations-0.1.3.dist-info/WHEEL
pytest_extra_durations-0.1.3.dist-info/entry_points.txt
pytest_extra_durations-0.1.3.dist-info/top_level.txt
pytest_extra_durations-0.1.3.dist-info/RECORD
