Metadata-Version: 2.1
Name: pytest-extra-durations
Version: 0.1.3
Summary: A pytest plugin to get durations on a per-function basis and per module basis.
Home-page: https://github.com/gabrieldemarmiesse/pytest-extra-durations
Author: Gabriel de Marmiesse
Author-email: gabrieldemarmiesse@gmail.com
Maintainer: Gabriel de Marmiesse
Maintainer-email: gabrieldemarmiesse@gmail.com
License: MIT
Platform: UNKNOWN
Classifier: Development Status :: 4 - Beta
Classifier: Framework :: Pytest
Classifier: Intended Audience :: Developers
Classifier: Topic :: Software Development :: Testing
Classifier: Programming Language :: Python
Classifier: Programming Language :: Python :: 3.5
Classifier: Programming Language :: Python :: 3.6
Classifier: Programming Language :: Python :: 3.7
Classifier: Programming Language :: Python :: 3.8
Classifier: Programming Language :: Python :: Implementation :: CPython
Classifier: Programming Language :: Python :: Implementation :: PyPy
Classifier: Operating System :: OS Independent
Classifier: License :: OSI Approved :: MIT License
Requires-Python: >=3.5
Requires-Dist: pytest (>=3.5.0)
